beemcp/__init__.py
beemcp/bee.py
beemcp/beemcp.py
beemcp/conversation.py
beemcp/fact.py
beemcp/location.py
beemcp/manual_testing.py
beemcp/todo.py
beemcp/utils.py
beemcp-0.3.0.dist-info/licenses/LICENSE
beemcp-0.3.0.dist-info/METADATA
beemcp-0.3.0.dist-info/WHEEL
beemcp-0.3.0.dist-info/entry_points.txt
beemcp-0.3.0.dist-info/top_level.txt
beemcp-0.3.0.dist-info/RECORD
