Metadata-Version: 2.4
Name: beemcp
Version: 0.3.0
Summary: A Model Context Protocol (MCP) server for Bee.computer lifelogging data (unofficial)
Author-email: Roger Pincombe <roger@pincombe.com>
Maintainer-email: Roger Pincombe <roger@pincombe.com>
License-Expression: MIT
Project-URL: Homepage, https://github.com/okgodoit/beemcp
Project-URL: Repository, https://github.com/okgodoit/beemcp
Project-URL: Bug Tracker, https://github.com/okgodoit/beemcp/issues
Keywords: mcp,model context protocol,bee.computer,bee ai,bee,lifelogging,ai,llm,chatbot
Classifier: Development Status :: 4 - Beta
Classifier: Intended Audience :: Developers
Classifier: Intended Audience :: End Users/Desktop
Classifier: Programming Language :: Python :: 3
Classifier: Programming Language :: Python :: 3.10
Classifier: Programming Language :: Python :: 3.11
Classifier: Programming Language :: Python :: 3.12
Classifier: Topic :: Scientific/Engineering :: Artificial Intelligence
Classifier: Operating System :: OS Independent
Requires-Python: >=3.10
License-File: LICENSE
Requires-Dist: mcp[cli]>=1.4.0
Requires-Dist: requests>=2.31.0
Requires-Dist: python-dotenv>=1.0.0
Dynamic: license-file
